{
    "os": "Linux-5.14.0-284.40.1.el9_2.x86_64-x86_64-with-glibc2.34",
    "python": "3.12.0",
    "heartbeatAt": "2024-05-03T12:05:19.045176",
    "startedAt": "2024-05-03T12:05:18.651345",
    "docker": null,
    "cuda": null,
    "args": [
        "--epochs=24",
        "--batch_size=16",
        "--input_size=128",
        "--train=True",
        "--model=ResNet152",
        "--lr=1e-3",
        "--momentum=0.9",
        "--weight_decay=1e-3"
    ],
    "state": "running",
    "program": "/scratch/yx3038/24Spring/ML/Final-Competition/src/main.py",
    "codePathLocal": "main.py",
    "codePath": "src/main.py",
    "git": {
        "remote": "https://github.com/Zephyr271828/Final-Competition.git",
        "commit": "2d9bdd36b5652f0d58465f6db86c98001cef279f"
    },
    "email": "1689079482@qq.com",
    "root": "/scratch/yx3038/24Spring/ML/Final-Competition",
    "host": "ga037.hpc.nyu.edu",
    "username": "yx3038",
    "executable": "/scratch/yx3038/penv/bin/python",
    "cpu_count": 80,
    "cpu_count_logical": 160,
    "cpu_freq": {
        "current": 3.059512499999992,
        "min": 800.0,
        "max": 3400.0
    },
    "cpu_freq_per_core": [
        {
            "current": 3.4,
            "min": 800.0,
            "max": 3400.0
        },
        {
            "current": 2.651,
            "min": 800.0,
            "max": 3400.0
        },
        {
            "current": 2.651,
            "min": 800.0,
            "max": 3400.0
        },
        {
            "current": 2.651,
            "min": 800.0,
            "max": 3400.0
        },
        {
            "current": 2.651,
            "min": 800.0,
            "max": 3400.0
        },
        {
            "current": 2.65,
            "min": 800.0,
            "max": 3400.0
        },
        {
            "current": 2.65,
            "min": 800.0,
            "max": 3400.0
        },
        {
            "current": 2.65,
            "min": 800.0,
            "max": 3400.0
        },
        {
            "current": 2.652,
            "min": 800.0,
            "max": 3400.0
        },
        {
            "current": 3.4,
            "min": 800.0,
            "max": 3400.0
        },
        {
            "current": 2.828,
            "min": 800.0,
            "max": 3400.0
        },
        {
            "current": 2.828,
            "min": 800.0,
            "max": 3400.0
        },
        {
            "current": 3.4,
            "min": 800.0,
            "max": 3400.0
        },
        {
            "current": 3.4,
            "min": 800.0,
            "max": 3400.0
        },
        {
            "current": 3.4,
            "min": 800.0,
            "max": 3400.0
        },
        {
            "current": 2.828,
            "min": 800.0,
            "max": 3400.0
        },
        {
            "current": 2.828,
            "min": 800.0,
            "max": 3400.0
        },
        {
            "current": 2.828,
            "min": 800.0,
            "max": 3400.0
        },
        {
            "current": 2.748,
            "min": 800.0,
            "max": 3400.0
        },
        {
            "current": 2.828,
            "min": 800.0,
            "max": 3400.0
        },
        {
            "current": 3.4,
            "min": 800.0,
            "max": 3400.0
        },
        {
            "current": 2.828,
            "min": 800.0,
            "max": 3400.0
        },
        {
            "current": 2.828,
            "min": 800.0,
            "max": 3400.0
        },
        {
            "current": 2.828,
            "min": 800.0,
            "max": 3400.0
        },
        {
            "current": 2.828,
            "min": 800.0,
            "max": 3400.0
        },
        {
            "current": 2.828,
            "min": 800.0,
            "max": 3400.0
        },
        {
            "current": 2.828,
            "min": 800.0,
            "max": 3400.0
        },
        {
            "current": 2.828,
            "min": 800.0,
            "max": 3400.0
        },
        {
            "current": 3.4,
            "min": 800.0,
            "max": 3400.0
        },
        {
            "current": 2.829,
            "min": 800.0,
            "max": 3400.0
        },
        {
            "current": 2.829,
            "min": 800.0,
            "max": 3400.0
        },
        {
            "current": 2.829,
            "min": 800.0,
            "max": 3400.0
        },
        {
            "current": 2.829,
            "min": 800.0,
            "max": 3400.0
        },
        {
            "current": 2.829,
            "min": 800.0,
            "max": 3400.0
        },
        {
            "current": 2.829,
            "min": 800.0,
            "max": 3400.0
        },
        {
            "current": 3.4,
            "min": 800.0,
            "max": 3400.0
        },
        {
            "current": 2.829,
            "min": 800.0,
            "max": 3400.0
        },
        {
            "current": 2.829,
            "min": 800.0,
            "max": 3400.0
        },
        {
            "current": 3.4,
            "min": 800.0,
            "max": 3400.0
        },
        {
            "current": 2.829,
            "min": 800.0,
            "max": 3400.0
        },
        {
            "current": 2.73,
            "min": 800.0,
            "max": 3400.0
        },
        {
            "current": 3.4,
            "min": 800.0,
            "max": 3400.0
        },
        {
            "current": 2.733,
            "min": 800.0,
            "max": 3400.0
        },
        {
            "current": 2.741,
            "min": 800.0,
            "max": 3400.0
        },
        {
            "current": 2.74,
            "min": 800.0,
            "max": 3400.0
        },
        {
            "current": 2.74,
            "min": 800.0,
            "max": 3400.0
        },
        {
            "current": 2.74,
            "min": 800.0,
            "max": 3400.0
        },
        {
            "current": 2.74,
            "min": 800.0,
            "max": 3400.0
        },
        {
            "current": 2.74,
            "min": 800.0,
            "max": 3400.0
        },
        {
            "current": 2.9,
            "min": 800.0,
            "max": 3400.0
        },
        {
            "current": 2.9,
            "min": 800.0,
            "max": 3400.0
        },
        {
            "current": 2.9,
            "min": 800.0,
            "max": 3400.0
        },
        {
            "current": 2.9,
            "min": 800.0,
            "max": 3400.0
        },
        {
            "current": 2.9,
            "min": 800.0,
            "max": 3400.0
        },
        {
            "current": 2.899,
            "min": 800.0,
            "max": 3400.0
        },
        {
            "current": 3.4,
            "min": 800.0,
            "max": 3400.0
        },
        {
            "current": 2.9,
            "min": 800.0,
            "max": 3400.0
        },
        {
            "current": 2.9,
            "min": 800.0,
            "max": 3400.0
        },
        {
            "current": 2.9,
            "min": 800.0,
            "max": 3400.0
        },
        {
            "current": 2.899,
            "min": 800.0,
            "max": 3400.0
        },
        {
            "current": 2.9,
            "min": 800.0,
            "max": 3400.0
        },
        {
            "current": 2.9,
            "min": 800.0,
            "max": 3400.0
        },
        {
            "current": 2.9,
            "min": 800.0,
            "max": 3400.0
        },
        {
            "current": 2.899,
            "min": 800.0,
            "max": 3400.0
        },
        {
            "current": 2.9,
            "min": 800.0,
            "max": 3400.0
        },
        {
            "current": 2.9,
            "min": 800.0,
            "max": 3400.0
        },
        {
            "current": 2.9,
            "min": 800.0,
            "max": 3400.0
        },
        {
            "current": 2.9,
            "min": 800.0,
            "max": 3400.0
        },
        {
            "current": 2.9,
            "min": 800.0,
            "max": 3400.0
        },
        {
            "current": 2.9,
            "min": 800.0,
            "max": 3400.0
        },
        {
            "current": 2.9,
            "min": 800.0,
            "max": 3400.0
        },
        {
            "current": 2.9,
            "min": 800.0,
            "max": 3400.0
        },
        {
            "current": 3.4,
            "min": 800.0,
            "max": 3400.0
        },
        {
            "current": 3.4,
            "min": 800.0,
            "max": 3400.0
        },
        {
            "current": 3.4,
            "min": 800.0,
            "max": 3400.0
        },
        {
            "current": 2.9,
            "min": 800.0,
            "max": 3400.0
        },
        {
            "current": 3.4,
            "min": 800.0,
            "max": 3400.0
        },
        {
            "current": 3.4,
            "min": 800.0,
            "max": 3400.0
        },
        {
            "current": 3.4,
            "min": 800.0,
            "max": 3400.0
        },
        {
            "current": 3.4,
            "min": 800.0,
            "max": 3400.0
        },
        {
            "current": 2.831,
            "min": 800.0,
            "max": 3400.0
        },
        {
            "current": 2.645,
            "min": 800.0,
            "max": 3400.0
        },
        {
            "current": 2.645,
            "min": 800.0,
            "max": 3400.0
        },
        {
            "current": 2.645,
            "min": 800.0,
            "max": 3400.0
        },
        {
            "current": 2.646,
            "min": 800.0,
            "max": 3400.0
        },
        {
            "current": 2.646,
            "min": 800.0,
            "max": 3400.0
        },
        {
            "current": 2.646,
            "min": 800.0,
            "max": 3400.0
        },
        {
            "current": 2.646,
            "min": 800.0,
            "max": 3400.0
        },
        {
            "current": 2.647,
            "min": 800.0,
            "max": 3400.0
        },
        {
            "current": 2.831,
            "min": 800.0,
            "max": 3400.0
        },
        {
            "current": 3.4,
            "min": 800.0,
            "max": 3400.0
        },
        {
            "current": 3.4,
            "min": 800.0,
            "max": 3400.0
        },
        {
            "current": 2.832,
            "min": 800.0,
            "max": 3400.0
        },
        {
            "current": 2.832,
            "min": 800.0,
            "max": 3400.0
        },
        {
            "current": 2.832,
            "min": 800.0,
            "max": 3400.0
        },
        {
            "current": 3.4,
            "min": 800.0,
            "max": 3400.0
        },
        {
            "current": 3.4,
            "min": 800.0,
            "max": 3400.0
        },
        {
            "current": 3.4,
            "min": 800.0,
            "max": 3400.0
        },
        {
            "current": 3.4,
            "min": 800.0,
            "max": 3400.0
        },
        {
            "current": 3.4,
            "min": 800.0,
            "max": 3400.0
        },
        {
            "current": 2.832,
            "min": 800.0,
            "max": 3400.0
        },
        {
            "current": 3.4,
            "min": 800.0,
            "max": 3400.0
        },
        {
            "current": 3.4,
            "min": 800.0,
            "max": 3400.0
        },
        {
            "current": 3.4,
            "min": 800.0,
            "max": 3400.0
        },
        {
            "current": 3.4,
            "min": 800.0,
            "max": 3400.0
        },
        {
            "current": 3.4,
            "min": 800.0,
            "max": 3400.0
        },
        {
            "current": 3.4,
            "min": 800.0,
            "max": 3400.0
        },
        {
            "current": 3.4,
            "min": 800.0,
            "max": 3400.0
        },
        {
            "current": 2.832,
            "min": 800.0,
            "max": 3400.0
        },
        {
            "current": 3.4,
            "min": 800.0,
            "max": 3400.0
        },
        {
            "current": 3.4,
            "min": 800.0,
            "max": 3400.0
        },
        {
            "current": 3.4,
            "min": 800.0,
            "max": 3400.0
        },
        {
            "current": 3.4,
            "min": 800.0,
            "max": 3400.0
        },
        {
            "current": 3.4,
            "min": 800.0,
            "max": 3400.0
        },
        {
            "current": 3.4,
            "min": 800.0,
            "max": 3400.0
        },
        {
            "current": 2.833,
            "min": 800.0,
            "max": 3400.0
        },
        {
            "current": 3.4,
            "min": 800.0,
            "max": 3400.0
        },
        {
            "current": 3.4,
            "min": 800.0,
            "max": 3400.0
        },
        {
            "current": 2.833,
            "min": 800.0,
            "max": 3400.0
        },
        {
            "current": 3.4,
            "min": 800.0,
            "max": 3400.0
        },
        {
            "current": 2.745,
            "min": 800.0,
            "max": 3400.0
        },
        {
            "current": 2.884,
            "min": 800.0,
            "max": 3400.0
        },
        {
            "current": 2.749,
            "min": 800.0,
            "max": 3400.0
        },
        {
            "current": 2.745,
            "min": 800.0,
            "max": 3400.0
        },
        {
            "current": 2.743,
            "min": 800.0,
            "max": 3400.0
        },
        {
            "current": 2.743,
            "min": 800.0,
            "max": 3400.0
        },
        {
            "current": 2.743,
            "min": 800.0,
            "max": 3400.0
        },
        {
            "current": 2.743,
            "min": 800.0,
            "max": 3400.0
        },
        {
            "current": 2.742,
            "min": 800.0,
            "max": 3400.0
        },
        {
            "current": 3.4,
            "min": 800.0,
            "max": 3400.0
        },
        {
            "current": 3.4,
            "min": 800.0,
            "max": 3400.0
        },
        {
            "current": 3.4,
            "min": 800.0,
            "max": 3400.0
        },
        {
            "current": 3.4,
            "min": 800.0,
            "max": 3400.0
        },
        {
            "current": 3.4,
            "min": 800.0,
            "max": 3400.0
        },
        {
            "current": 3.4,
            "min": 800.0,
            "max": 3400.0
        },
        {
            "current": 2.899,
            "min": 800.0,
            "max": 3400.0
        },
        {
            "current": 3.4,
            "min": 800.0,
            "max": 3400.0
        },
        {
            "current": 3.4,
            "min": 800.0,
            "max": 3400.0
        },
        {
            "current": 3.4,
            "min": 800.0,
            "max": 3400.0
        },
        {
            "current": 3.4,
            "min": 800.0,
            "max": 3400.0
        },
        {
            "current": 3.4,
            "min": 800.0,
            "max": 3400.0
        },
        {
            "current": 3.4,
            "min": 800.0,
            "max": 3400.0
        },
        {
            "current": 3.4,
            "min": 800.0,
            "max": 3400.0
        },
        {
            "current": 3.4,
            "min": 800.0,
            "max": 3400.0
        },
        {
            "current": 3.4,
            "min": 800.0,
            "max": 3400.0
        },
        {
            "current": 3.4,
            "min": 800.0,
            "max": 3400.0
        },
        {
            "current": 3.4,
            "min": 800.0,
            "max": 3400.0
        },
        {
            "current": 3.4,
            "min": 800.0,
            "max": 3400.0
        },
        {
            "current": 3.4,
            "min": 800.0,
            "max": 3400.0
        },
        {
            "current": 3.4,
            "min": 800.0,
            "max": 3400.0
        },
        {
            "current": 3.4,
            "min": 800.0,
            "max": 3400.0
        },
        {
            "current": 3.4,
            "min": 800.0,
            "max": 3400.0
        },
        {
            "current": 2.9,
            "min": 800.0,
            "max": 3400.0
        },
        {
            "current": 2.899,
            "min": 800.0,
            "max": 3400.0
        },
        {
            "current": 2.9,
            "min": 800.0,
            "max": 3400.0
        },
        {
            "current": 3.4,
            "min": 800.0,
            "max": 3400.0
        },
        {
            "current": 3.4,
            "min": 800.0,
            "max": 3400.0
        },
        {
            "current": 2.9,
            "min": 800.0,
            "max": 3400.0
        },
        {
            "current": 3.4,
            "min": 800.0,
            "max": 3400.0
        },
        {
            "current": 3.4,
            "min": 800.0,
            "max": 3400.0
        }
    ],
    "disk": {
        "/": {
            "total": 78.08685302734375,
            "used": 21.327980041503906
        }
    },
    "gpu": "NVIDIA A100-SXM4-80GB",
    "gpu_count": 1,
    "gpu_devices": [
        {
            "name": "NVIDIA A100-SXM4-80GB",
            "memory_total": 85899345920
        }
    ],
    "memory": {
        "total": 1007.0006446838379
    }
}
